{"skeleton":{"hash":"mkO6fEdUXK/RC/chv9QImiuRrRE","spine":"2.1.27","width":100,"height":100,"images":"./res/"},"bones":[{"name":"root"},{"name":"cover","parent":"root","length":59.92,"x":0.25,"y":-30.2,"rotation":90},{"name":"skill","parent":"root"},{"name":"light","parent":"skill"},{"name":"quan","parent":"skill"}],"slots":[{"name":"cover","bone":"cover","attachment":"cover"},{"name":"light","bone":"light"},{"name":"quan","bone":"quan","attachment":"quan2","blend":"screen"}],"skins":{"default":{"light":{"skill_1":{"x":11.26,"y":0.62,"width":200,"height":120},"skill_2":{"x":11.26,"y":0.62,"width":200,"height":120},"skill_3":{"x":11.26,"y":0.62,"width":200,"height":120},"skill_4":{"x":11.26,"y":0.62,"width":200,"height":120}},"quan":{"quan2":{"width":100,"height":100}}},"aoe_cheng":{"cover":{"cover":{"name":"skill_aoe","x":30.2,"y":0.25,"rotation":-90,"width":78,"height":78}}},"aoe_hong":{"cover":{"cover":{"name":"skill_aoe","x":30.2,"y":0.25,"rotation":-90,"width":78,"height":78}}},"aoe_huang":{"cover":{"cover":{"name":"skill_aoe","x":30.2,"y":0.25,"rotation":-90,"width":78,"height":78}}},"aoe_lan":{"cover":{"cover":{"name":"skill_aoe","x":30.2,"y":0.25,"rotation":-90,"width":78,"height":78}}},"aoe_lv":{"cover":{"cover":{"name":"skill_aoe","x":30.2,"y":0.25,"rotation":-90,"width":78,"height":78}}},"aoe_zi":{"cover":{"cover":{"name":"skill_aoe","x":30.2,"y":0.25,"rotation":-90,"width":78,"height":78}}},"cai":{},"h_cheng":{"cover":{"cover":{"name":"skill_h","x":30.2,"y":0.25,"rotation":-90,"width":78,"height":78}}},"h_hong":{"cover":{"cover":{"name":"skill_h","x":30.2,"y":0.25,"rotation":-90,"width":78,"height":78}}},"h_huang":{"cover":{"cover":{"name":"skill_h","x":30.2,"y":0.25,"rotation":-90,"width":78,"height":78}}},"h_lan":{"cover":{"cover":{"name":"skill_h","x":30.2,"y":0.25,"rotation":-90,"width":78,"height":78}}},"h_lv":{"cover":{"cover":{"name":"skill_h","x":30.2,"y":0.25,"rotation":-90,"width":78,"height":78}}},"h_zi":{"cover":{"cover":{"name":"skill_h","x":30.2,"y":0.25,"rotation":-90,"width":78,"height":78}}},"v_cheng":{"cover":{"cover":{"name":"skill_v","x":30.2,"y":0.25,"rotation":-90,"width":78,"height":78}}},"v_hong":{"cover":{"cover":{"name":"skill_v","x":30.2,"y":0.25,"rotation":-90,"width":78,"height":78}}},"v_huang":{"cover":{"cover":{"name":"skill_v","x":30.2,"y":0.25,"rotation":-90,"width":78,"height":78}}},"v_lan":{"cover":{"cover":{"name":"skill_v","x":30.2,"y":0.25,"rotation":-90,"width":78,"height":78}}},"v_lv":{"cover":{"cover":{"name":"skill_v","x":30.2,"y":0.25,"rotation":-90,"width":78,"height":78}}},"v_zi":{"cover":{"cover":{"name":"skill_v","x":30.2,"y":0.25,"rotation":-90,"width":78,"height":78}}}},"events":{"fall":{}},"animations":{"down":{"slots":{"quan":{"attachment":[{"time":0,"name":null}]}},"bones":{"cover":{"scale":[{"time":0,"x":1,"y":1,"curve":[0.919,0.46,1,0.54]},{"time":0.1333,"x":0.744,"y":1.059,"curve":[0.919,0.46,1,0.54]},{"time":0.2333,"x":1,"y":1}]}}},"exchange_LR":{"slots":{"quan":{"attachment":[{"time":0,"name":null}]}},"bones":{"root":{"translate":[{"time":0.4666,"x":0,"y":0,"curve":"stepped"},{"time":0.6666,"x":0,"y":0},{"time":0.8666,"x":0.3,"y":0},{"time":1.0666,"x":0,"y":0}],"scale":[{"time":0,"x":1,"y":1},{"time":0.2,"x":1.5,"y":1.22},{"time":0.3666,"x":1,"y":1}]}}},"exchange_UD":{"slots":{"quan":{"attachment":[{"time":0,"name":null}]}},"bones":{"root":{"translate":[{"time":0,"x":0,"y":0},{"time":0.2,"x":0,"y":20},{"time":0.3666,"x":0,"y":0,"curve":"stepped"},{"time":0.4666,"x":0,"y":0,"curve":"stepped"},{"time":0.6666,"x":0,"y":0},{"time":0.8666,"x":0.3,"y":0},{"time":1.0666,"x":0,"y":0}],"scale":[{"time":0,"x":1,"y":1},{"time":0.2,"x":0.94,"y":1.29},{"time":0.3666,"x":1,"y":1}]}}},"fx_cai":{"slots":{"cover":{"color":[{"time":0,"color":"ffffffff"},{"time":0.3333,"color":"706e6dff"},{"time":1,"color":"ffffffff"}]},"quan":{"attachment":[{"time":0,"name":null}]}},"bones":{"root":{"scale":[{"time":0,"x":1,"y":1}]},"cover":{"scale":[{"time":0,"x":1,"y":1}]}}},"fx_skill":{"slots":{"quan":{"attachment":[{"time":0,"name":null}]}},"bones":{"root":{"scale":[{"time":0,"x":1,"y":1}]},"cover":{"scale":[{"time":0,"x":1,"y":1}]}}},"remove":{"slots":{"quan":{"attachment":[{"time":0,"name":null}]}},"bones":{"root":{"scale":[{"time":0,"x":1,"y":1},{"time":0.2,"x":0,"y":0}]}},"events":[{"time":0.1333,"name":"fall","string":"fall"}]},"select":{"slots":{"quan":{"attachment":[{"time":0,"name":null}]}}},"skill_show":{"slots":{"light":{"attachment":[{"time":0,"name":"skill_1"},{"time":0.1,"name":"skill_2"},{"time":0.2,"name":"skill_3"},{"time":0.3,"name":"skill_4"},{"time":0.4,"name":"skill_4"}],"color":[{"time":0.3,"color":"ffffffff"},{"time":0.4,"color":"ffffff00"}]},"quan":{"color":[{"time":0.1666,"color":"ffffff00"},{"time":0.5,"color":"f4f7ffff"},{"time":0.6666,"color":"eef3ff00"}]}},"bones":{"light":{"rotate":[{"time":0,"angle":0}],"translate":[{"time":0,"x":0,"y":0}],"scale":[{"time":0,"x":1.1,"y":1.1,"curve":[0.983,0.19,1,1]},{"time":0.1,"x":0.6,"y":0.6,"curve":[0,0,0.403,0.9]},{"time":0.4,"x":1,"y":1}]},"quan":{"translate":[{"time":0,"x":0,"y":0,"curve":"stepped"},{"time":0.1666,"x":0,"y":0,"curve":"stepped"},{"time":0.6666,"x":0,"y":0}],"scale":[{"time":0,"x":0,"y":0,"curve":"stepped"},{"time":0.1666,"x":0,"y":0},{"time":0.6666,"x":1.5,"y":1.5}]}}},"static":{"slots":{"cover":{"attachment":[{"time":0,"name":"cover"}]},"quan":{"attachment":[{"time":0,"name":null}]}},"bones":{"cover":{"scale":[{"time":0,"x":1,"y":1}]},"root":{"translate":[{"time":0,"x":0,"y":0}],"scale":[{"time":0,"x":1,"y":1}]}}}}}